{
  "appId": "10090795",
  "history": [
    {
      "date": "2024-12-28",
      "count": "14367"
    },
    {
      "date": "2024-12-29",
      "count": "14368"
    },
    {
      "date": "2024-12-30",
      "count": "14379"
    },
    {
      "date": "2024-12-31",
      "count": "14399"
    },
    {
      "date": "2025-01-01",
      "count": "14419"
    },
    {
      "date": "2025-01-02",
      "count": "14427"
    },
    {
      "date": "2025-01-03",
      "count": "14464"
    },
    {
      "date": "2025-01-04",
      "count": "14488"
    },
    {
      "date": "2025-01-05",
      "count": "14503"
    },
    {
      "date": "2025-01-06",
      "count": "14511"
    },
    {
      "date": "2025-01-07",
      "count": "14548"
    },
    {
      "date": "2025-01-08",
      "count": "14587"
    },
    {
      "date": "2025-01-09",
      "count": "14633"
    },
    {
      "date": "2025-01-10",
      "count": "14672"
    },
    {
      "date": "2025-01-11",
      "count": "14716"
    },
    {
      "date": "2025-01-12",
      "count": "14730"
    },
    {
      "date": "2025-01-13",
      "count": "14742"
    },
    {
      "date": "2025-01-14",
      "count": "14769"
    },
    {
      "date": "2025-01-15",
      "count": "14819"
    },
    {
      "date": "2025-01-16",
      "count": "14866"
    },
    {
      "date": "2025-01-17",
      "count": "14918"
    },
    {
      "date": "2025-01-18",
      "count": "14959"
    },
    {
      "date": "2025-01-19",
      "count": "14965"
    },
    {
      "date": "2025-01-20",
      "count": "14977"
    },
    {
      "date": "2025-01-21",
      "count": "15013"
    },
    {
      "date": "2025-01-22",
      "count": "15070"
    },
    {
      "date": "2025-01-23",
      "count": "15121"
    },
    {
      "date": "2025-01-24",
      "count": "15170"
    },
    {
      "date": "2025-01-25",
      "count": "15205"
    },
    {
      "date": "2025-01-26",
      "count": "15213"
    },
    {
      "date": "2025-01-27",
      "count": "15222"
    },
    {
      "date": "2025-01-28",
      "count": "15261"
    },
    {
      "date": "2025-01-29",
      "count": "15307"
    },
    {
      "date": "2025-01-30",
      "count": "15356"
    },
    {
      "date": "2025-01-31",
      "count": "15404"
    },
    {
      "date": "2025-02-01",
      "count": "15433"
    },
    {
      "date": "2025-02-02",
      "count": "15442"
    },
    {
      "date": "2025-02-03",
      "count": "15454"
    },
    {
      "date": "2025-02-04",
      "count": "15503"
    },
    {
      "date": "2025-02-05",
      "count": "15559"
    },
    {
      "date": "2025-02-06",
      "count": "15625"
    },
    {
      "date": "2025-02-07",
      "count": "15676"
    },
    {
      "date": "2025-02-08",
      "count": "15710"
    },
    {
      "date": "2025-02-09",
      "count": "15727"
    },
    {
      "date": "2025-02-10",
      "count": "15734"
    },
    {
      "date": "2025-02-11",
      "count": "15779"
    },
    {
      "date": "2025-02-12",
      "count": "15833"
    },
    {
      "date": "2025-02-13",
      "count": "15870"
    },
    {
      "date": "2025-02-14",
      "count": "15915"
    },
    {
      "date": "2025-02-15",
      "count": "15956"
    },
    {
      "date": "2025-02-16",
      "count": "15974"
    },
    {
      "date": "2025-02-17",
      "count": "15992"
    },
    {
      "date": "2025-02-18",
      "count": "16028"
    },
    {
      "date": "2025-02-19",
      "count": "16072"
    },
    {
      "date": "2025-02-20",
      "count": "16129"
    },
    {
      "date": "2025-02-21",
      "count": "16175"
    },
    {
      "date": "2025-02-22",
      "count": "16223"
    },
    {
      "date": "2025-02-23",
      "count": "16234"
    },
    {
      "date": "2025-02-24",
      "count": "16241"
    },
    {
      "date": "2025-02-25",
      "count": "16279"
    },
    {
      "date": "2025-02-26",
      "count": "16326"
    },
    {
      "date": "2025-02-27",
      "count": "16367"
    },
    {
      "date": "2025-02-28",
      "count": "16417"
    },
    {
      "date": "2025-03-01",
      "count": "16451"
    },
    {
      "date": "2025-03-02",
      "count": "16464"
    },
    {
      "date": "2025-03-03",
      "count": "16474"
    },
    {
      "date": "2025-03-04",
      "count": "16512"
    },
    {
      "date": "2025-03-05",
      "count": "16540"
    },
    {
      "date": "2025-03-06",
      "count": "16573"
    },
    {
      "date": "2025-03-07",
      "count": "16617"
    },
    {
      "date": "2025-03-08",
      "count": "16648"
    },
    {
      "date": "2025-03-09",
      "count": "16658"
    },
    {
      "date": "2025-03-10",
      "count": "16668"
    },
    {
      "date": "2025-03-11",
      "count": "16704"
    },
    {
      "date": "2025-03-12",
      "count": "16748"
    },
    {
      "date": "2025-03-13",
      "count": "16781"
    },
    {
      "date": "2025-03-14",
      "count": "16810"
    },
    {
      "date": "2025-03-15",
      "count": "16843"
    },
    {
      "date": "2025-03-16",
      "count": "16850"
    },
    {
      "date": "2025-03-17",
      "count": "16861"
    },
    {
      "date": "2025-03-18",
      "count": "16894"
    },
    {
      "date": "2025-03-19",
      "count": "16941"
    },
    {
      "date": "2025-03-20",
      "count": "16980"
    },
    {
      "date": "2025-03-21",
      "count": "17013"
    },
    {
      "date": "2025-03-22",
      "count": "17044"
    },
    {
      "date": "2025-03-23",
      "count": "17057"
    },
    {
      "date": "2025-03-24",
      "count": "17062"
    },
    {
      "date": "2025-03-25",
      "count": "17108"
    },
    {
      "date": "2025-03-26",
      "count": "17145"
    },
    {
      "date": "2025-03-27",
      "count": "17184"
    },
    {
      "date": "2025-03-28",
      "count": "17221"
    },
    {
      "date": "2025-03-29",
      "count": "17252"
    },
    {
      "date": "2025-03-30",
      "count": "17258"
    },
    {
      "date": "2025-03-31",
      "count": "17263"
    },
    {
      "date": "2025-04-01",
      "count": "17299"
    },
    {
      "date": "2025-04-02",
      "count": "17331"
    },
    {
      "date": "2025-04-03",
      "count": "17363"
    },
    {
      "date": "2025-04-04",
      "count": "17397"
    },
    {
      "date": "2025-04-05",
      "count": "17429"
    },
    {
      "date": "2025-04-06",
      "count": "17437"
    },
    {
      "date": "2025-04-07",
      "count": "17447"
    },
    {
      "date": "2025-04-08",
      "count": "17486"
    },
    {
      "date": "2025-04-09",
      "count": "17526"
    },
    {
      "date": "2025-04-10",
      "count": "17566"
    },
    {
      "date": "2025-04-11",
      "count": "17597"
    },
    {
      "date": "2025-04-12",
      "count": "17622"
    },
    {
      "date": "2025-04-13",
      "count": "17636"
    },
    {
      "date": "2025-04-14",
      "count": "17643"
    },
    {
      "date": "2025-04-15",
      "count": "17686"
    },
    {
      "date": "2025-04-16",
      "count": "17718"
    },
    {
      "date": "2025-04-17",
      "count": "17754"
    },
    {
      "date": "2025-04-18",
      "count": "17777"
    },
    {
      "date": "2025-04-19",
      "count": "17796"
    },
    {
      "date": "2025-04-20",
      "count": "17805"
    },
    {
      "date": "2025-04-21",
      "count": "17812"
    },
    {
      "date": "2025-04-22",
      "count": "17844"
    },
    {
      "date": "2025-04-23",
      "count": "17885"
    },
    {
      "date": "2025-04-24",
      "count": "17916"
    },
    {
      "date": "2025-04-25",
      "count": "17943"
    },
    {
      "date": "2025-04-26",
      "count": "17969"
    },
    {
      "date": "2025-04-27",
      "count": "17971"
    },
    {
      "date": "2025-04-28",
      "count": "17977"
    },
    {
      "date": "2025-04-29",
      "count": "18002"
    },
    {
      "date": "2025-04-30",
      "count": "18034"
    },
    {
      "date": "2025-05-01",
      "count": "18062"
    },
    {
      "date": "2025-05-02",
      "count": "18094"
    },
    {
      "date": "2025-05-03",
      "count": "18116"
    },
    {
      "date": "2025-05-04",
      "count": "18120"
    },
    {
      "date": "2025-05-05",
      "count": "18129"
    },
    {
      "date": "2025-05-06",
      "count": "18160"
    },
    {
      "date": "2025-05-07",
      "count": "18203"
    },
    {
      "date": "2025-05-08",
      "count": "18249"
    },
    {
      "date": "2025-05-09",
      "count": "18278"
    },
    {
      "date": "2025-05-10",
      "count": "18311"
    },
    {
      "date": "2025-05-11",
      "count": "18316"
    },
    {
      "date": "2025-05-12",
      "count": "18322"
    },
    {
      "date": "2025-05-13",
      "count": "18361"
    },
    {
      "date": "2025-05-14",
      "count": "18411"
    },
    {
      "date": "2025-05-15",
      "count": "18452"
    },
    {
      "date": "2025-05-16",
      "count": "18483"
    },
    {
      "date": "2025-05-17",
      "count": "18514"
    },
    {
      "date": "2025-05-18",
      "count": "18521"
    },
    {
      "date": "2025-05-19",
      "count": "18529"
    },
    {
      "date": "2025-05-20",
      "count": "18563"
    },
    {
      "date": "2025-05-21",
      "count": "18606"
    },
    {
      "date": "2025-05-22",
      "count": "18653"
    },
    {
      "date": "2025-05-23",
      "count": "18695"
    },
    {
      "date": "2025-05-24",
      "count": "18726"
    },
    {
      "date": "2025-05-25",
      "count": "18733"
    },
    {
      "date": "2025-05-26",
      "count": "18739"
    },
    {
      "date": "2025-05-27",
      "count": "18762"
    },
    {
      "date": "2025-05-28",
      "count": "18791"
    },
    {
      "date": "2025-05-29",
      "count": "18827"
    },
    {
      "date": "2025-05-30",
      "count": "18857"
    },
    {
      "date": "2025-05-31",
      "count": "18876"
    },
    {
      "date": "2025-06-01",
      "count": "18883"
    },
    {
      "date": "2025-06-02",
      "count": "18888"
    },
    {
      "date": "2025-06-03",
      "count": "18917"
    },
    {
      "date": "2025-06-04",
      "count": "18946"
    },
    {
      "date": "2025-06-05",
      "count": "18987"
    },
    {
      "date": "2025-06-06",
      "count": "19022"
    },
    {
      "date": "2025-06-07",
      "count": "19038"
    },
    {
      "date": "2025-06-08",
      "count": "19041"
    },
    {
      "date": "2025-06-09",
      "count": "19043"
    },
    {
      "date": "2025-06-10",
      "count": "19093"
    },
    {
      "date": "2025-06-11",
      "count": "19099"
    },
    {
      "date": "2025-06-12",
      "count": "19125"
    },
    {
      "date": "2025-06-13",
      "count": "19163"
    },
    {
      "date": "2025-06-14",
      "count": "19192"
    },
    {
      "date": "2025-06-15",
      "count": "19197"
    },
    {
      "date": "2025-06-16",
      "count": "19204"
    },
    {
      "date": "2025-06-17",
      "count": "19224"
    },
    {
      "date": "2025-06-18",
      "count": "19264"
    },
    {
      "date": "2025-06-19",
      "count": "19298"
    },
    {
      "date": "2025-06-20",
      "count": "19325"
    },
    {
      "date": "2025-06-21",
      "count": "19355"
    },
    {
      "date": "2025-06-22",
      "count": "19362"
    },
    {
      "date": "2025-06-23",
      "count": "19381"
    },
    {
      "date": "2025-06-24",
      "count": "19410"
    },
    {
      "date": "2025-06-25",
      "count": "19439"
    },
    {
      "date": "2025-06-26",
      "count": "19471"
    },
    {
      "date": "2025-06-27",
      "count": "19500"
    },
    {
      "date": "2025-06-28",
      "count": "19532"
    },
    {
      "date": "2025-06-29",
      "count": "19535"
    },
    {
      "date": "2025-06-30",
      "count": "19538"
    },
    {
      "date": "2025-07-01",
      "count": "19566"
    },
    {
      "date": "2025-07-02",
      "count": "19598"
    },
    {
      "date": "2025-07-03",
      "count": "19637"
    },
    {
      "date": "2025-07-04",
      "count": "19662"
    },
    {
      "date": "2025-07-05",
      "count": "19671"
    },
    {
      "date": "2025-07-06",
      "count": "19677"
    },
    {
      "date": "2025-07-07",
      "count": "19683"
    },
    {
      "date": "2025-07-08",
      "count": "19725"
    },
    {
      "date": "2025-07-09",
      "count": "19769"
    },
    {
      "date": "2025-07-10",
      "count": "19806"
    },
    {
      "date": "2025-07-11",
      "count": "19850"
    },
    {
      "date": "2025-07-12",
      "count": "19878"
    },
    {
      "date": "2025-07-13",
      "count": "19886"
    },
    {
      "date": "2025-07-14",
      "count": "19894"
    },
    {
      "date": "2025-07-15",
      "count": "19929"
    },
    {
      "date": "2025-07-16",
      "count": "19965"
    },
    {
      "date": "2025-07-17",
      "count": "19998"
    },
    {
      "date": "2025-07-18",
      "count": "20029"
    },
    {
      "date": "2025-07-19",
      "count": "20061"
    },
    {
      "date": "2025-07-20",
      "count": "20063"
    },
    {
      "date": "2025-07-21",
      "count": "20071"
    },
    {
      "date": "2025-07-22",
      "count": "20107"
    },
    {
      "date": "2025-07-23",
      "count": "20142"
    },
    {
      "date": "2025-07-24",
      "count": "20177"
    },
    {
      "date": "2025-07-25",
      "count": "20207"
    },
    {
      "date": "2025-07-26",
      "count": "20235"
    },
    {
      "date": "2025-07-27",
      "count": "20240"
    },
    {
      "date": "2025-07-28",
      "count": "20249"
    },
    {
      "date": "2025-07-29",
      "count": "20285"
    },
    {
      "date": "2025-07-30",
      "count": "20318"
    },
    {
      "date": "2025-07-31",
      "count": "20343"
    },
    {
      "date": "2025-08-01",
      "count": "20373"
    },
    {
      "date": "2025-08-02",
      "count": "20403"
    },
    {
      "date": "2025-08-03",
      "count": "20413"
    },
    {
      "date": "2025-08-04",
      "count": "20421"
    },
    {
      "date": "2025-08-05",
      "count": "20444"
    },
    {
      "date": "2025-08-06",
      "count": "20473"
    },
    {
      "date": "2025-08-07",
      "count": "20510"
    },
    {
      "date": "2025-08-08",
      "count": "20547"
    },
    {
      "date": "2025-08-09",
      "count": "20578"
    },
    {
      "date": "2025-08-10",
      "count": "20587"
    },
    {
      "date": "2025-08-11",
      "count": "20595"
    },
    {
      "date": "2025-08-12",
      "count": "20624"
    },
    {
      "date": "2025-08-13",
      "count": "20656"
    },
    {
      "date": "2025-08-14",
      "count": "20687"
    },
    {
      "date": "2025-08-15",
      "count": "20714"
    },
    {
      "date": "2025-08-16",
      "count": "20744"
    },
    {
      "date": "2025-08-17",
      "count": "20751"
    },
    {
      "date": "2025-08-18",
      "count": "20762"
    },
    {
      "date": "2025-08-19",
      "count": "20797"
    },
    {
      "date": "2025-08-20",
      "count": "20847"
    },
    {
      "date": "2025-08-21",
      "count": "20864"
    },
    {
      "date": "2025-08-22",
      "count": "20899"
    },
    {
      "date": "2025-08-23",
      "count": "20922"
    },
    {
      "date": "2025-08-24",
      "count": "20928"
    },
    {
      "date": "2025-08-25",
      "count": "20937"
    },
    {
      "date": "2025-08-26",
      "count": "20963"
    },
    {
      "date": "2025-08-27",
      "count": "20998"
    },
    {
      "date": "2025-08-28",
      "count": "21037"
    },
    {
      "date": "2025-08-29",
      "count": "21070"
    },
    {
      "date": "2025-08-30",
      "count": "21098"
    },
    {
      "date": "2025-08-31",
      "count": "21103"
    },
    {
      "date": "2025-09-01",
      "count": "21108"
    },
    {
      "date": "2025-09-02",
      "count": "21124"
    },
    {
      "date": "2025-09-03",
      "count": "21153"
    },
    {
      "date": "2025-09-04",
      "count": "21186"
    },
    {
      "date": "2025-09-05",
      "count": "21220"
    },
    {
      "date": "2025-09-06",
      "count": "21246"
    },
    {
      "date": "2025-09-07",
      "count": "21254"
    },
    {
      "date": "2025-09-08",
      "count": "21259"
    },
    {
      "date": "2025-09-09",
      "count": "21293"
    },
    {
      "date": "2025-09-10",
      "count": "21324"
    },
    {
      "date": "2025-09-11",
      "count": "21361"
    },
    {
      "date": "2025-09-12",
      "count": "21383"
    },
    {
      "date": "2025-09-13",
      "count": "21407"
    },
    {
      "date": "2025-09-14",
      "count": "21415"
    },
    {
      "date": "2025-09-15",
      "count": "21425"
    },
    {
      "date": "2025-09-16",
      "count": "21453"
    },
    {
      "date": "2025-09-17",
      "count": "21487"
    },
    {
      "date": "2025-09-18",
      "count": "21526"
    },
    {
      "date": "2025-09-19",
      "count": "21550"
    },
    {
      "date": "2025-09-20",
      "count": "21569"
    },
    {
      "date": "2025-09-21",
      "count": "21572"
    },
    {
      "date": "2025-09-22",
      "count": "21578"
    },
    {
      "date": "2025-09-23",
      "count": "21599"
    },
    {
      "date": "2025-09-24",
      "count": "21626"
    },
    {
      "date": "2025-09-25",
      "count": "21656"
    },
    {
      "date": "2025-09-26",
      "count": "21687"
    },
    {
      "date": "2025-09-27",
      "count": "21706"
    },
    {
      "date": "2025-09-28",
      "count": "21709"
    },
    {
      "date": "2025-09-29",
      "count": "21717"
    },
    {
      "date": "2025-09-30",
      "count": "21755"
    },
    {
      "date": "2025-10-01",
      "count": "21792"
    },
    {
      "date": "2025-10-02",
      "count": "21823"
    },
    {
      "date": "2025-10-03",
      "count": "21849"
    },
    {
      "date": "2025-10-04",
      "count": "21871"
    },
    {
      "date": "2025-10-05",
      "count": "21878"
    },
    {
      "date": "2025-10-06",
      "count": "21881"
    },
    {
      "date": "2025-10-07",
      "count": "21903"
    },
    {
      "date": "2025-10-08",
      "count": "21937"
    },
    {
      "date": "2025-10-09",
      "count": "21970"
    },
    {
      "date": "2025-10-10",
      "count": "22013"
    },
    {
      "date": "2025-10-11",
      "count": "22040"
    },
    {
      "date": "2025-10-12",
      "count": "22053"
    },
    {
      "date": "2025-10-13",
      "count": "22068"
    },
    {
      "date": "2025-10-14",
      "count": "22096"
    },
    {
      "date": "2025-10-15",
      "count": "22126"
    },
    {
      "date": "2025-10-16",
      "count": "22159"
    },
    {
      "date": "2025-10-17",
      "count": "22197"
    },
    {
      "date": "2025-10-18",
      "count": "22210"
    },
    {
      "date": "2025-10-19",
      "count": "22218"
    },
    {
      "date": "2025-10-20",
      "count": "22223"
    },
    {
      "date": "2025-10-21",
      "count": "22251"
    },
    {
      "date": "2025-10-22",
      "count": "22288"
    },
    {
      "date": "2025-10-23",
      "count": "22322"
    },
    {
      "date": "2025-10-24",
      "count": "22358"
    },
    {
      "date": "2025-10-25",
      "count": "22383"
    },
    {
      "date": "2025-10-26",
      "count": "22389"
    },
    {
      "date": "2025-10-27",
      "count": "22391"
    },
    {
      "date": "2025-10-28",
      "count": "22421"
    },
    {
      "date": "2025-10-29",
      "count": "22450"
    },
    {
      "date": "2025-10-30",
      "count": "22477"
    },
    {
      "date": "2025-10-31",
      "count": "22513"
    },
    {
      "date": "2025-11-01",
      "count": "22535"
    },
    {
      "date": "2025-11-02",
      "count": "22538"
    },
    {
      "date": "2025-11-03",
      "count": "22544"
    },
    {
      "date": "2025-11-04",
      "count": "22574"
    },
    {
      "date": "2025-11-05",
      "count": "22607"
    },
    {
      "date": "2025-11-06",
      "count": "22633"
    },
    {
      "date": "2025-11-07",
      "count": "22662"
    },
    {
      "date": "2025-11-08",
      "count": "22688"
    },
    {
      "date": "2025-11-09",
      "count": "22694"
    },
    {
      "date": "2025-11-10",
      "count": "22704"
    },
    {
      "date": "2025-11-11",
      "count": "22734"
    },
    {
      "date": "2025-11-12",
      "count": "22758"
    },
    {
      "date": "2025-11-13",
      "count": "22786"
    }
  ]
}
