{
  "appId": "10150307",
  "history": [
    {
      "date": "2024-12-28",
      "count": "431"
    },
    {
      "date": "2024-12-29",
      "count": "432"
    },
    {
      "date": "2024-12-30",
      "count": "433"
    },
    {
      "date": "2024-12-31",
      "count": "436"
    },
    {
      "date": "2025-01-01",
      "count": "443"
    },
    {
      "date": "2025-01-02",
      "count": "444"
    },
    {
      "date": "2025-01-03",
      "count": "447"
    },
    {
      "date": "2025-01-04",
      "count": "448"
    },
    {
      "date": "2025-01-05",
      "count": "450"
    },
    {
      "date": "2025-01-06",
      "count": "451"
    },
    {
      "date": "2025-01-07",
      "count": "454"
    },
    {
      "date": "2025-01-08",
      "count": "460"
    },
    {
      "date": "2025-01-09",
      "count": "469"
    },
    {
      "date": "2025-01-10",
      "count": "471"
    },
    {
      "date": "2025-01-11",
      "count": "472"
    },
    {
      "date": "2025-01-12",
      "count": "474"
    },
    {
      "date": "2025-01-13",
      "count": "475"
    },
    {
      "date": "2025-01-14",
      "count": "478"
    },
    {
      "date": "2025-01-15",
      "count": "477"
    },
    {
      "date": "2025-01-16",
      "count": "481"
    },
    {
      "date": "2025-01-17",
      "count": "488"
    },
    {
      "date": "2025-01-18",
      "count": "490"
    },
    {
      "date": "2025-01-19",
      "count": "492"
    },
    {
      "date": "2025-01-20",
      "count": "493"
    },
    {
      "date": "2025-01-21",
      "count": "497"
    },
    {
      "date": "2025-01-22",
      "count": "501"
    },
    {
      "date": "2025-01-23",
      "count": "505"
    },
    {
      "date": "2025-01-24",
      "count": "509"
    },
    {
      "date": "2025-01-25",
      "count": "513"
    },
    {
      "date": "2025-01-26",
      "count": "516"
    },
    {
      "date": "2025-01-27",
      "count": "517"
    },
    {
      "date": "2025-01-28",
      "count": "518"
    },
    {
      "date": "2025-01-29",
      "count": "526"
    },
    {
      "date": "2025-01-30",
      "count": "531"
    },
    {
      "date": "2025-01-31",
      "count": "540"
    },
    {
      "date": "2025-02-01",
      "count": "548"
    },
    {
      "date": "2025-02-02",
      "count": "550"
    },
    {
      "date": "2025-02-03",
      "count": "551"
    },
    {
      "date": "2025-02-04",
      "count": "556"
    },
    {
      "date": "2025-02-05",
      "count": "563"
    },
    {
      "date": "2025-02-06",
      "count": "572"
    },
    {
      "date": "2025-02-07",
      "count": "579"
    },
    {
      "date": "2025-02-08",
      "count": "584"
    },
    {
      "date": "2025-02-09",
      "count": "587"
    },
    {
      "date": "2025-02-10",
      "count": "587"
    },
    {
      "date": "2025-02-11",
      "count": "593"
    },
    {
      "date": "2025-02-12",
      "count": "602"
    },
    {
      "date": "2025-02-13",
      "count": "613"
    },
    {
      "date": "2025-02-14",
      "count": "621"
    },
    {
      "date": "2025-02-15",
      "count": "623"
    },
    {
      "date": "2025-02-16",
      "count": "625"
    },
    {
      "date": "2025-02-17",
      "count": "627"
    },
    {
      "date": "2025-02-18",
      "count": "632"
    },
    {
      "date": "2025-02-19",
      "count": "640"
    },
    {
      "date": "2025-02-20",
      "count": "644"
    },
    {
      "date": "2025-02-21",
      "count": "655"
    },
    {
      "date": "2025-02-22",
      "count": "659"
    },
    {
      "date": "2025-02-23",
      "count": "662"
    },
    {
      "date": "2025-02-24",
      "count": "664"
    },
    {
      "date": "2025-02-25",
      "count": "670"
    },
    {
      "date": "2025-02-26",
      "count": "680"
    },
    {
      "date": "2025-02-27",
      "count": "689"
    },
    {
      "date": "2025-02-28",
      "count": "694"
    },
    {
      "date": "2025-03-01",
      "count": "698"
    },
    {
      "date": "2025-03-02",
      "count": "703"
    },
    {
      "date": "2025-03-03",
      "count": "704"
    },
    {
      "date": "2025-03-04",
      "count": "710"
    },
    {
      "date": "2025-03-05",
      "count": "717"
    },
    {
      "date": "2025-03-06",
      "count": "722"
    },
    {
      "date": "2025-03-07",
      "count": "728"
    },
    {
      "date": "2025-03-08",
      "count": "737"
    },
    {
      "date": "2025-03-09",
      "count": "737"
    },
    {
      "date": "2025-03-10",
      "count": "740"
    },
    {
      "date": "2025-03-11",
      "count": "747"
    },
    {
      "date": "2025-03-12",
      "count": "748"
    },
    {
      "date": "2025-03-13",
      "count": "758"
    },
    {
      "date": "2025-03-14",
      "count": "761"
    },
    {
      "date": "2025-03-15",
      "count": "767"
    },
    {
      "date": "2025-03-16",
      "count": "771"
    },
    {
      "date": "2025-03-17",
      "count": "773"
    },
    {
      "date": "2025-03-18",
      "count": "776"
    },
    {
      "date": "2025-03-19",
      "count": "785"
    },
    {
      "date": "2025-03-20",
      "count": "789"
    },
    {
      "date": "2025-03-21",
      "count": "796"
    },
    {
      "date": "2025-03-22",
      "count": "799"
    },
    {
      "date": "2025-03-23",
      "count": "800"
    },
    {
      "date": "2025-03-24",
      "count": "800"
    },
    {
      "date": "2025-03-25",
      "count": "802"
    },
    {
      "date": "2025-03-26",
      "count": "812"
    },
    {
      "date": "2025-03-27",
      "count": "818"
    },
    {
      "date": "2025-03-28",
      "count": "823"
    },
    {
      "date": "2025-03-29",
      "count": "824"
    },
    {
      "date": "2025-03-30",
      "count": "825"
    },
    {
      "date": "2025-03-31",
      "count": "825"
    },
    {
      "date": "2025-04-01",
      "count": "829"
    },
    {
      "date": "2025-04-02",
      "count": "834"
    },
    {
      "date": "2025-04-03",
      "count": "841"
    },
    {
      "date": "2025-04-04",
      "count": "842"
    },
    {
      "date": "2025-04-05",
      "count": "846"
    },
    {
      "date": "2025-04-06",
      "count": "847"
    },
    {
      "date": "2025-04-07",
      "count": "849"
    },
    {
      "date": "2025-04-08",
      "count": "851"
    },
    {
      "date": "2025-04-09",
      "count": "858"
    },
    {
      "date": "2025-04-10",
      "count": "859"
    },
    {
      "date": "2025-04-11",
      "count": "867"
    },
    {
      "date": "2025-04-12",
      "count": "870"
    },
    {
      "date": "2025-04-13",
      "count": "870"
    },
    {
      "date": "2025-04-14",
      "count": "870"
    },
    {
      "date": "2025-04-15",
      "count": "876"
    },
    {
      "date": "2025-04-16",
      "count": "878"
    },
    {
      "date": "2025-04-17",
      "count": "882"
    },
    {
      "date": "2025-04-18",
      "count": "888"
    },
    {
      "date": "2025-04-19",
      "count": "890"
    },
    {
      "date": "2025-04-20",
      "count": "891"
    },
    {
      "date": "2025-04-21",
      "count": "894"
    },
    {
      "date": "2025-04-22",
      "count": "899"
    },
    {
      "date": "2025-04-23",
      "count": "906"
    },
    {
      "date": "2025-04-24",
      "count": "912"
    },
    {
      "date": "2025-04-25",
      "count": "919"
    },
    {
      "date": "2025-04-26",
      "count": "920"
    },
    {
      "date": "2025-04-27",
      "count": "920"
    },
    {
      "date": "2025-04-28",
      "count": "922"
    },
    {
      "date": "2025-04-29",
      "count": "927"
    },
    {
      "date": "2025-04-30",
      "count": "938"
    },
    {
      "date": "2025-05-01",
      "count": "945"
    },
    {
      "date": "2025-05-02",
      "count": "952"
    },
    {
      "date": "2025-05-03",
      "count": "960"
    },
    {
      "date": "2025-05-04",
      "count": "961"
    },
    {
      "date": "2025-05-05",
      "count": "961"
    },
    {
      "date": "2025-05-06",
      "count": "967"
    },
    {
      "date": "2025-05-07",
      "count": "975"
    },
    {
      "date": "2025-05-08",
      "count": "978"
    },
    {
      "date": "2025-05-09",
      "count": "983"
    },
    {
      "date": "2025-05-10",
      "count": "992"
    },
    {
      "date": "2025-05-11",
      "count": "994"
    },
    {
      "date": "2025-05-12",
      "count": "995"
    },
    {
      "date": "2025-05-13",
      "count": "997"
    },
    {
      "date": "2025-05-14",
      "count": "1002"
    },
    {
      "date": "2025-05-15",
      "count": "1017"
    },
    {
      "date": "2025-05-16",
      "count": "1022"
    },
    {
      "date": "2025-05-17",
      "count": "1024"
    },
    {
      "date": "2025-05-18",
      "count": "1024"
    },
    {
      "date": "2025-05-19",
      "count": "1026"
    },
    {
      "date": "2025-05-20",
      "count": "1036"
    },
    {
      "date": "2025-05-21",
      "count": "1043"
    },
    {
      "date": "2025-05-22",
      "count": "1050"
    },
    {
      "date": "2025-05-23",
      "count": "1053"
    },
    {
      "date": "2025-05-24",
      "count": "1054"
    },
    {
      "date": "2025-05-25",
      "count": "1054"
    },
    {
      "date": "2025-05-26",
      "count": "1054"
    },
    {
      "date": "2025-05-27",
      "count": "1057"
    },
    {
      "date": "2025-05-28",
      "count": "1066"
    },
    {
      "date": "2025-05-29",
      "count": "1075"
    },
    {
      "date": "2025-05-30",
      "count": "1077"
    },
    {
      "date": "2025-05-31",
      "count": "1079"
    },
    {
      "date": "2025-06-01",
      "count": "1080"
    },
    {
      "date": "2025-06-02",
      "count": "1082"
    },
    {
      "date": "2025-06-03",
      "count": "1085"
    },
    {
      "date": "2025-06-04",
      "count": "1090"
    },
    {
      "date": "2025-06-05",
      "count": "1099"
    },
    {
      "date": "2025-06-06",
      "count": "1103"
    },
    {
      "date": "2025-06-07",
      "count": "1110"
    },
    {
      "date": "2025-06-08",
      "count": "1112"
    },
    {
      "date": "2025-06-09",
      "count": "1114"
    },
    {
      "date": "2025-06-10",
      "count": "1127"
    },
    {
      "date": "2025-06-11",
      "count": "1126"
    },
    {
      "date": "2025-06-12",
      "count": "1139"
    },
    {
      "date": "2025-06-13",
      "count": "1148"
    },
    {
      "date": "2025-06-14",
      "count": "1152"
    },
    {
      "date": "2025-06-15",
      "count": "1154"
    },
    {
      "date": "2025-06-16",
      "count": "1155"
    },
    {
      "date": "2025-06-17",
      "count": "1159"
    },
    {
      "date": "2025-06-18",
      "count": "1164"
    },
    {
      "date": "2025-06-19",
      "count": "1166"
    },
    {
      "date": "2025-06-20",
      "count": "1170"
    },
    {
      "date": "2025-06-21",
      "count": "1175"
    },
    {
      "date": "2025-06-22",
      "count": "1176"
    },
    {
      "date": "2025-06-23",
      "count": "1179"
    },
    {
      "date": "2025-06-24",
      "count": "1189"
    },
    {
      "date": "2025-06-25",
      "count": "1197"
    },
    {
      "date": "2025-06-26",
      "count": "1201"
    },
    {
      "date": "2025-06-27",
      "count": "1209"
    },
    {
      "date": "2025-06-28",
      "count": "1218"
    },
    {
      "date": "2025-06-29",
      "count": "1220"
    },
    {
      "date": "2025-06-30",
      "count": "1221"
    },
    {
      "date": "2025-07-01",
      "count": "1228"
    },
    {
      "date": "2025-07-02",
      "count": "1238"
    },
    {
      "date": "2025-07-03",
      "count": "1241"
    },
    {
      "date": "2025-07-04",
      "count": "1245"
    },
    {
      "date": "2025-07-05",
      "count": "1247"
    },
    {
      "date": "2025-07-06",
      "count": "1249"
    },
    {
      "date": "2025-07-07",
      "count": "1251"
    },
    {
      "date": "2025-07-08",
      "count": "1261"
    },
    {
      "date": "2025-07-09",
      "count": "1272"
    },
    {
      "date": "2025-07-10",
      "count": "1281"
    },
    {
      "date": "2025-07-11",
      "count": "1286"
    },
    {
      "date": "2025-07-12",
      "count": "1296"
    },
    {
      "date": "2025-07-13",
      "count": "1298"
    },
    {
      "date": "2025-07-14",
      "count": "1299"
    },
    {
      "date": "2025-07-15",
      "count": "1303"
    },
    {
      "date": "2025-07-16",
      "count": "1315"
    },
    {
      "date": "2025-07-17",
      "count": "1319"
    },
    {
      "date": "2025-07-18",
      "count": "1324"
    },
    {
      "date": "2025-07-19",
      "count": "1330"
    },
    {
      "date": "2025-07-20",
      "count": "1334"
    },
    {
      "date": "2025-07-21",
      "count": "1336"
    },
    {
      "date": "2025-07-22",
      "count": "1344"
    },
    {
      "date": "2025-07-23",
      "count": "1356"
    },
    {
      "date": "2025-07-24",
      "count": "1362"
    },
    {
      "date": "2025-07-25",
      "count": "1369"
    },
    {
      "date": "2025-07-26",
      "count": "1376"
    },
    {
      "date": "2025-07-27",
      "count": "1380"
    },
    {
      "date": "2025-07-28",
      "count": "1381"
    },
    {
      "date": "2025-07-29",
      "count": "1389"
    },
    {
      "date": "2025-07-30",
      "count": "1401"
    },
    {
      "date": "2025-07-31",
      "count": "1413"
    },
    {
      "date": "2025-08-01",
      "count": "1422"
    },
    {
      "date": "2025-08-02",
      "count": "1429"
    },
    {
      "date": "2025-08-03",
      "count": "1433"
    },
    {
      "date": "2025-08-04",
      "count": "1433"
    },
    {
      "date": "2025-08-05",
      "count": "1440"
    },
    {
      "date": "2025-08-06",
      "count": "1444"
    },
    {
      "date": "2025-08-07",
      "count": "1451"
    },
    {
      "date": "2025-08-08",
      "count": "1460"
    },
    {
      "date": "2025-08-09",
      "count": "1471"
    },
    {
      "date": "2025-08-10",
      "count": "1474"
    },
    {
      "date": "2025-08-11",
      "count": "1478"
    },
    {
      "date": "2025-08-12",
      "count": "1488"
    },
    {
      "date": "2025-08-13",
      "count": "1496"
    },
    {
      "date": "2025-08-14",
      "count": "1505"
    },
    {
      "date": "2025-08-15",
      "count": "1512"
    },
    {
      "date": "2025-08-16",
      "count": "1517"
    },
    {
      "date": "2025-08-17",
      "count": "1518"
    },
    {
      "date": "2025-08-18",
      "count": "1521"
    },
    {
      "date": "2025-08-19",
      "count": "1532"
    },
    {
      "date": "2025-08-20",
      "count": "1537"
    },
    {
      "date": "2025-08-21",
      "count": "1548"
    },
    {
      "date": "2025-08-22",
      "count": "1551"
    },
    {
      "date": "2025-08-23",
      "count": "1554"
    },
    {
      "date": "2025-08-24",
      "count": "1561"
    },
    {
      "date": "2025-08-25",
      "count": "1564"
    },
    {
      "date": "2025-08-26",
      "count": "1571"
    },
    {
      "date": "2025-08-27",
      "count": "1580"
    },
    {
      "date": "2025-08-28",
      "count": "1590"
    },
    {
      "date": "2025-08-29",
      "count": "1601"
    },
    {
      "date": "2025-08-30",
      "count": "1604"
    },
    {
      "date": "2025-08-31",
      "count": "1607"
    },
    {
      "date": "2025-09-01",
      "count": "1610"
    },
    {
      "date": "2025-09-02",
      "count": "1615"
    },
    {
      "date": "2025-09-03",
      "count": "1620"
    },
    {
      "date": "2025-09-04",
      "count": "1630"
    },
    {
      "date": "2025-09-05",
      "count": "1640"
    },
    {
      "date": "2025-09-06",
      "count": "1650"
    },
    {
      "date": "2025-09-07",
      "count": "1653"
    },
    {
      "date": "2025-09-08",
      "count": "1658"
    },
    {
      "date": "2025-09-09",
      "count": "1671"
    },
    {
      "date": "2025-09-10",
      "count": "1675"
    },
    {
      "date": "2025-09-11",
      "count": "1682"
    },
    {
      "date": "2025-09-12",
      "count": "1699"
    },
    {
      "date": "2025-09-13",
      "count": "1700"
    },
    {
      "date": "2025-09-14",
      "count": "1703"
    },
    {
      "date": "2025-09-15",
      "count": "1703"
    },
    {
      "date": "2025-09-16",
      "count": "1708"
    },
    {
      "date": "2025-09-17",
      "count": "1719"
    },
    {
      "date": "2025-09-18",
      "count": "1730"
    },
    {
      "date": "2025-09-19",
      "count": "1739"
    },
    {
      "date": "2025-09-20",
      "count": "1743"
    },
    {
      "date": "2025-09-21",
      "count": "1745"
    },
    {
      "date": "2025-09-22",
      "count": "1750"
    },
    {
      "date": "2025-09-23",
      "count": "1758"
    },
    {
      "date": "2025-09-24",
      "count": "1764"
    },
    {
      "date": "2025-09-25",
      "count": "1778"
    },
    {
      "date": "2025-09-26",
      "count": "1784"
    },
    {
      "date": "2025-09-27",
      "count": "1791"
    },
    {
      "date": "2025-09-28",
      "count": "1791"
    },
    {
      "date": "2025-09-29",
      "count": "1795"
    },
    {
      "date": "2025-09-30",
      "count": "1806"
    },
    {
      "date": "2025-10-01",
      "count": "1812"
    },
    {
      "date": "2025-10-02",
      "count": "1824"
    },
    {
      "date": "2025-10-03",
      "count": "1834"
    },
    {
      "date": "2025-10-04",
      "count": "1845"
    },
    {
      "date": "2025-10-05",
      "count": "1846"
    },
    {
      "date": "2025-10-06",
      "count": "1848"
    },
    {
      "date": "2025-10-07",
      "count": "1855"
    },
    {
      "date": "2025-10-08",
      "count": "1866"
    },
    {
      "date": "2025-10-09",
      "count": "1876"
    },
    {
      "date": "2025-10-10",
      "count": "1884"
    },
    {
      "date": "2025-10-11",
      "count": "1892"
    },
    {
      "date": "2025-10-12",
      "count": "1895"
    },
    {
      "date": "2025-10-13",
      "count": "1901"
    },
    {
      "date": "2025-10-14",
      "count": "1905"
    },
    {
      "date": "2025-10-15",
      "count": "1913"
    },
    {
      "date": "2025-10-16",
      "count": "1919"
    },
    {
      "date": "2025-10-17",
      "count": "1929"
    },
    {
      "date": "2025-10-18",
      "count": "1938"
    },
    {
      "date": "2025-10-19",
      "count": "1941"
    },
    {
      "date": "2025-10-20",
      "count": "1945"
    },
    {
      "date": "2025-10-21",
      "count": "1952"
    },
    {
      "date": "2025-10-22",
      "count": "1964"
    },
    {
      "date": "2025-10-23",
      "count": "1973"
    },
    {
      "date": "2025-10-24",
      "count": "1980"
    },
    {
      "date": "2025-10-25",
      "count": "1988"
    },
    {
      "date": "2025-10-26",
      "count": "1989"
    },
    {
      "date": "2025-10-27",
      "count": "1993"
    },
    {
      "date": "2025-10-28",
      "count": "2007"
    },
    {
      "date": "2025-10-29",
      "count": "2016"
    },
    {
      "date": "2025-10-30",
      "count": "2027"
    },
    {
      "date": "2025-10-31",
      "count": "2028"
    },
    {
      "date": "2025-11-01",
      "count": "2038"
    },
    {
      "date": "2025-11-02",
      "count": "2040"
    },
    {
      "date": "2025-11-03",
      "count": "2046"
    },
    {
      "date": "2025-11-04",
      "count": "2052"
    },
    {
      "date": "2025-11-05",
      "count": "2061"
    },
    {
      "date": "2025-11-06",
      "count": "2070"
    },
    {
      "date": "2025-11-07",
      "count": "2086"
    },
    {
      "date": "2025-11-08",
      "count": "2089"
    },
    {
      "date": "2025-11-09",
      "count": "2090"
    },
    {
      "date": "2025-11-10",
      "count": "2093"
    },
    {
      "date": "2025-11-11",
      "count": "2097"
    },
    {
      "date": "2025-11-12",
      "count": "2105"
    },
    {
      "date": "2025-11-13",
      "count": "2122"
    },
    {
      "date": "2025-11-14",
      "count": "2134"
    },
    {
      "date": "2025-11-15",
      "count": "2141"
    },
    {
      "date": "2025-11-16",
      "count": "2144"
    }
  ]
}
