{
  "appId": "41098",
  "history": [
    {
      "date": "2024-12-28",
      "count": "2154"
    },
    {
      "date": "2024-12-29",
      "count": "2154"
    },
    {
      "date": "2024-12-30",
      "count": "2155"
    },
    {
      "date": "2024-12-31",
      "count": "2155"
    },
    {
      "date": "2025-01-01",
      "count": "2158"
    },
    {
      "date": "2025-01-02",
      "count": "2161"
    },
    {
      "date": "2025-01-03",
      "count": "2163"
    },
    {
      "date": "2025-01-04",
      "count": "2163"
    },
    {
      "date": "2025-01-05",
      "count": "2163"
    },
    {
      "date": "2025-01-06",
      "count": "2165"
    },
    {
      "date": "2025-01-07",
      "count": "2168"
    },
    {
      "date": "2025-01-08",
      "count": "2168"
    },
    {
      "date": "2025-01-09",
      "count": "2170"
    },
    {
      "date": "2025-01-10",
      "count": "2175"
    },
    {
      "date": "2025-01-11",
      "count": "2179"
    },
    {
      "date": "2025-01-12",
      "count": "2181"
    },
    {
      "date": "2025-01-13",
      "count": "2180"
    },
    {
      "date": "2025-01-14",
      "count": "2181"
    },
    {
      "date": "2025-01-15",
      "count": "2183"
    },
    {
      "date": "2025-01-16",
      "count": "2185"
    },
    {
      "date": "2025-01-17",
      "count": "2191"
    },
    {
      "date": "2025-01-18",
      "count": "2193"
    },
    {
      "date": "2025-01-19",
      "count": "2195"
    },
    {
      "date": "2025-01-20",
      "count": "2196"
    },
    {
      "date": "2025-01-21",
      "count": "2198"
    },
    {
      "date": "2025-01-22",
      "count": "2203"
    },
    {
      "date": "2025-01-23",
      "count": "2207"
    },
    {
      "date": "2025-01-24",
      "count": "2208"
    },
    {
      "date": "2025-01-25",
      "count": "2211"
    },
    {
      "date": "2025-01-26",
      "count": "2212"
    },
    {
      "date": "2025-01-27",
      "count": "2214"
    },
    {
      "date": "2025-01-28",
      "count": "2216"
    },
    {
      "date": "2025-01-29",
      "count": "2220"
    },
    {
      "date": "2025-01-30",
      "count": "2220"
    },
    {
      "date": "2025-01-31",
      "count": "2227"
    },
    {
      "date": "2025-02-01",
      "count": "2236"
    },
    {
      "date": "2025-02-02",
      "count": "2238"
    },
    {
      "date": "2025-02-03",
      "count": "2239"
    },
    {
      "date": "2025-02-04",
      "count": "2242"
    },
    {
      "date": "2025-02-05",
      "count": "2244"
    },
    {
      "date": "2025-02-06",
      "count": "2248"
    },
    {
      "date": "2025-02-07",
      "count": "2248"
    },
    {
      "date": "2025-02-08",
      "count": "2252"
    },
    {
      "date": "2025-02-09",
      "count": "2254"
    },
    {
      "date": "2025-02-10",
      "count": "2254"
    },
    {
      "date": "2025-02-11",
      "count": "2259"
    },
    {
      "date": "2025-02-12",
      "count": "2261"
    },
    {
      "date": "2025-02-13",
      "count": "2263"
    },
    {
      "date": "2025-02-14",
      "count": "2264"
    },
    {
      "date": "2025-02-15",
      "count": "2268"
    },
    {
      "date": "2025-02-16",
      "count": "2270"
    },
    {
      "date": "2025-02-17",
      "count": "2271"
    },
    {
      "date": "2025-02-18",
      "count": "2272"
    },
    {
      "date": "2025-02-19",
      "count": "2272"
    },
    {
      "date": "2025-02-20",
      "count": "2277"
    },
    {
      "date": "2025-02-21",
      "count": "2280"
    },
    {
      "date": "2025-02-22",
      "count": "2287"
    },
    {
      "date": "2025-02-23",
      "count": "2287"
    },
    {
      "date": "2025-02-24",
      "count": "2287"
    },
    {
      "date": "2025-02-25",
      "count": "2288"
    },
    {
      "date": "2025-02-26",
      "count": "2289"
    },
    {
      "date": "2025-02-27",
      "count": "2290"
    },
    {
      "date": "2025-02-28",
      "count": "2293"
    },
    {
      "date": "2025-03-01",
      "count": "2296"
    },
    {
      "date": "2025-03-02",
      "count": "2298"
    },
    {
      "date": "2025-03-03",
      "count": "2300"
    },
    {
      "date": "2025-03-04",
      "count": "2305"
    },
    {
      "date": "2025-03-05",
      "count": "2309"
    },
    {
      "date": "2025-03-06",
      "count": "2313"
    },
    {
      "date": "2025-03-07",
      "count": "2314"
    },
    {
      "date": "2025-03-08",
      "count": "2316"
    },
    {
      "date": "2025-03-09",
      "count": "2316"
    },
    {
      "date": "2025-03-10",
      "count": "2316"
    },
    {
      "date": "2025-03-11",
      "count": "2316"
    },
    {
      "date": "2025-03-12",
      "count": "2321"
    },
    {
      "date": "2025-03-13",
      "count": "2323"
    },
    {
      "date": "2025-03-14",
      "count": "2325"
    },
    {
      "date": "2025-03-15",
      "count": "2326"
    },
    {
      "date": "2025-03-16",
      "count": "2326"
    },
    {
      "date": "2025-03-17",
      "count": "2327"
    },
    {
      "date": "2025-03-18",
      "count": "2328"
    },
    {
      "date": "2025-03-19",
      "count": "2329"
    },
    {
      "date": "2025-03-20",
      "count": "2332"
    },
    {
      "date": "2025-03-21",
      "count": "2333"
    },
    {
      "date": "2025-03-22",
      "count": "2334"
    },
    {
      "date": "2025-03-23",
      "count": "2337"
    },
    {
      "date": "2025-03-24",
      "count": "2338"
    },
    {
      "date": "2025-03-25",
      "count": "2340"
    },
    {
      "date": "2025-03-26",
      "count": "2344"
    },
    {
      "date": "2025-03-27",
      "count": "2346"
    },
    {
      "date": "2025-03-28",
      "count": "2350"
    },
    {
      "date": "2025-03-29",
      "count": "2354"
    },
    {
      "date": "2025-03-30",
      "count": "2354"
    },
    {
      "date": "2025-03-31",
      "count": "2358"
    },
    {
      "date": "2025-04-01",
      "count": "2358"
    },
    {
      "date": "2025-04-02",
      "count": "2358"
    },
    {
      "date": "2025-04-03",
      "count": "2363"
    },
    {
      "date": "2025-04-04",
      "count": "2367"
    },
    {
      "date": "2025-04-05",
      "count": "2369"
    },
    {
      "date": "2025-04-06",
      "count": "2368"
    },
    {
      "date": "2025-04-07",
      "count": "2368"
    },
    {
      "date": "2025-04-08",
      "count": "2370"
    },
    {
      "date": "2025-04-09",
      "count": "2370"
    },
    {
      "date": "2025-04-10",
      "count": "2375"
    },
    {
      "date": "2025-04-11",
      "count": "2377"
    },
    {
      "date": "2025-04-12",
      "count": "2380"
    },
    {
      "date": "2025-04-13",
      "count": "2380"
    },
    {
      "date": "2025-04-14",
      "count": "2380"
    },
    {
      "date": "2025-04-15",
      "count": "2379"
    },
    {
      "date": "2025-04-16",
      "count": "2382"
    },
    {
      "date": "2025-04-17",
      "count": "2384"
    },
    {
      "date": "2025-04-18",
      "count": "2389"
    },
    {
      "date": "2025-04-19",
      "count": "2392"
    },
    {
      "date": "2025-04-20",
      "count": "2393"
    },
    {
      "date": "2025-04-21",
      "count": "2395"
    },
    {
      "date": "2025-04-22",
      "count": "2396"
    },
    {
      "date": "2025-04-23",
      "count": "2399"
    },
    {
      "date": "2025-04-24",
      "count": "2400"
    },
    {
      "date": "2025-04-25",
      "count": "2400"
    },
    {
      "date": "2025-04-26",
      "count": "2400"
    },
    {
      "date": "2025-04-27",
      "count": "2400"
    },
    {
      "date": "2025-04-28",
      "count": "2400"
    },
    {
      "date": "2025-04-29",
      "count": "2401"
    },
    {
      "date": "2025-04-30",
      "count": "2402"
    },
    {
      "date": "2025-05-01",
      "count": "2404"
    },
    {
      "date": "2025-05-02",
      "count": "2404"
    },
    {
      "date": "2025-05-03",
      "count": "2407"
    },
    {
      "date": "2025-05-04",
      "count": "2409"
    },
    {
      "date": "2025-05-05",
      "count": "2410"
    },
    {
      "date": "2025-05-06",
      "count": "2412"
    },
    {
      "date": "2025-05-07",
      "count": "2411"
    },
    {
      "date": "2025-05-08",
      "count": "2416"
    },
    {
      "date": "2025-05-09",
      "count": "2420"
    },
    {
      "date": "2025-05-10",
      "count": "2422"
    },
    {
      "date": "2025-05-11",
      "count": "2422"
    },
    {
      "date": "2025-05-12",
      "count": "2422"
    },
    {
      "date": "2025-05-13",
      "count": "2425"
    },
    {
      "date": "2025-05-14",
      "count": "2428"
    },
    {
      "date": "2025-05-15",
      "count": "2428"
    },
    {
      "date": "2025-05-16",
      "count": "2431"
    },
    {
      "date": "2025-05-17",
      "count": "2431"
    },
    {
      "date": "2025-05-18",
      "count": "2431"
    },
    {
      "date": "2025-05-19",
      "count": "2431"
    },
    {
      "date": "2025-05-20",
      "count": "2431"
    },
    {
      "date": "2025-05-21",
      "count": "2434"
    },
    {
      "date": "2025-05-22",
      "count": "2435"
    },
    {
      "date": "2025-05-23",
      "count": "2436"
    },
    {
      "date": "2025-05-24",
      "count": "2439"
    },
    {
      "date": "2025-05-25",
      "count": "2441"
    },
    {
      "date": "2025-05-26",
      "count": "2442"
    },
    {
      "date": "2025-05-27",
      "count": "2443"
    },
    {
      "date": "2025-05-28",
      "count": "2442"
    },
    {
      "date": "2025-05-29",
      "count": "2444"
    },
    {
      "date": "2025-05-30",
      "count": "2445"
    },
    {
      "date": "2025-05-31",
      "count": "2446"
    },
    {
      "date": "2025-06-01",
      "count": "2446"
    },
    {
      "date": "2025-06-02",
      "count": "2447"
    },
    {
      "date": "2025-06-03",
      "count": "2449"
    },
    {
      "date": "2025-06-04",
      "count": "2450"
    },
    {
      "date": "2025-06-05",
      "count": "2450"
    },
    {
      "date": "2025-06-06",
      "count": "2450"
    },
    {
      "date": "2025-06-07",
      "count": "2451"
    },
    {
      "date": "2025-06-08",
      "count": "2451"
    },
    {
      "date": "2025-06-09",
      "count": "2451"
    },
    {
      "date": "2025-06-10",
      "count": "2455"
    },
    {
      "date": "2025-06-11",
      "count": "2456"
    },
    {
      "date": "2025-06-12",
      "count": "2458"
    },
    {
      "date": "2025-06-13",
      "count": "2462"
    },
    {
      "date": "2025-06-14",
      "count": "2464"
    },
    {
      "date": "2025-06-15",
      "count": "2464"
    },
    {
      "date": "2025-06-16",
      "count": "2466"
    },
    {
      "date": "2025-06-17",
      "count": "2465"
    },
    {
      "date": "2025-06-18",
      "count": "2465"
    },
    {
      "date": "2025-06-19",
      "count": "2467"
    },
    {
      "date": "2025-06-20",
      "count": "2469"
    },
    {
      "date": "2025-06-21",
      "count": "2469"
    },
    {
      "date": "2025-06-22",
      "count": "2469"
    },
    {
      "date": "2025-06-23",
      "count": "2469"
    },
    {
      "date": "2025-06-24",
      "count": "2470"
    },
    {
      "date": "2025-06-25",
      "count": "2472"
    },
    {
      "date": "2025-06-26",
      "count": "2475"
    },
    {
      "date": "2025-06-27",
      "count": "2479"
    },
    {
      "date": "2025-06-28",
      "count": "2481"
    },
    {
      "date": "2025-06-29",
      "count": "2481"
    },
    {
      "date": "2025-06-30",
      "count": "2481"
    },
    {
      "date": "2025-07-01",
      "count": "2482"
    },
    {
      "date": "2025-07-02",
      "count": "2485"
    },
    {
      "date": "2025-07-03",
      "count": "2485"
    },
    {
      "date": "2025-07-04",
      "count": "2486"
    },
    {
      "date": "2025-07-05",
      "count": "2488"
    },
    {
      "date": "2025-07-06",
      "count": "2488"
    },
    {
      "date": "2025-07-07",
      "count": "2489"
    },
    {
      "date": "2025-07-08",
      "count": "2490"
    },
    {
      "date": "2025-07-09",
      "count": "2492"
    },
    {
      "date": "2025-07-10",
      "count": "2496"
    },
    {
      "date": "2025-07-11",
      "count": "2498"
    },
    {
      "date": "2025-07-12",
      "count": "2499"
    },
    {
      "date": "2025-07-13",
      "count": "2499"
    },
    {
      "date": "2025-07-14",
      "count": "2499"
    },
    {
      "date": "2025-07-15",
      "count": "2500"
    },
    {
      "date": "2025-07-16",
      "count": "2502"
    },
    {
      "date": "2025-07-17",
      "count": "2502"
    },
    {
      "date": "2025-07-18",
      "count": "2504"
    },
    {
      "date": "2025-07-19",
      "count": "2506"
    },
    {
      "date": "2025-07-20",
      "count": "2508"
    },
    {
      "date": "2025-07-21",
      "count": "2509"
    },
    {
      "date": "2025-07-22",
      "count": "2508"
    },
    {
      "date": "2025-07-23",
      "count": "2509"
    },
    {
      "date": "2025-07-24",
      "count": "2512"
    },
    {
      "date": "2025-07-25",
      "count": "2511"
    },
    {
      "date": "2025-07-26",
      "count": "2514"
    },
    {
      "date": "2025-07-27",
      "count": "2514"
    },
    {
      "date": "2025-07-28",
      "count": "2515"
    },
    {
      "date": "2025-07-29",
      "count": "2517"
    },
    {
      "date": "2025-07-30",
      "count": "2517"
    },
    {
      "date": "2025-07-31",
      "count": "2519"
    },
    {
      "date": "2025-08-01",
      "count": "2520"
    },
    {
      "date": "2025-08-02",
      "count": "2520"
    },
    {
      "date": "2025-08-03",
      "count": "2520"
    },
    {
      "date": "2025-08-04",
      "count": "2520"
    },
    {
      "date": "2025-08-05",
      "count": "2523"
    },
    {
      "date": "2025-08-06",
      "count": "2524"
    },
    {
      "date": "2025-08-07",
      "count": "2528"
    },
    {
      "date": "2025-08-08",
      "count": "2530"
    },
    {
      "date": "2025-08-09",
      "count": "2533"
    },
    {
      "date": "2025-08-10",
      "count": "2533"
    },
    {
      "date": "2025-08-11",
      "count": "2534"
    },
    {
      "date": "2025-08-12",
      "count": "2534"
    },
    {
      "date": "2025-08-13",
      "count": "2534"
    },
    {
      "date": "2025-08-14",
      "count": "2536"
    },
    {
      "date": "2025-08-15",
      "count": "2538"
    },
    {
      "date": "2025-08-16",
      "count": "2538"
    },
    {
      "date": "2025-08-17",
      "count": "2538"
    },
    {
      "date": "2025-08-18",
      "count": "2538"
    },
    {
      "date": "2025-08-19",
      "count": "2543"
    },
    {
      "date": "2025-08-20",
      "count": "2545"
    },
    {
      "date": "2025-08-21",
      "count": "2546"
    },
    {
      "date": "2025-08-22",
      "count": "2547"
    },
    {
      "date": "2025-08-23",
      "count": "2547"
    },
    {
      "date": "2025-08-24",
      "count": "2549"
    },
    {
      "date": "2025-08-25",
      "count": "2550"
    },
    {
      "date": "2025-08-26",
      "count": "2554"
    },
    {
      "date": "2025-08-27",
      "count": "2561"
    },
    {
      "date": "2025-08-28",
      "count": "2565"
    },
    {
      "date": "2025-08-29",
      "count": "2567"
    },
    {
      "date": "2025-08-30",
      "count": "2567"
    },
    {
      "date": "2025-08-31",
      "count": "2567"
    },
    {
      "date": "2025-09-01",
      "count": "2567"
    },
    {
      "date": "2025-09-02",
      "count": "2570"
    },
    {
      "date": "2025-09-03",
      "count": "2574"
    },
    {
      "date": "2025-09-04",
      "count": "2576"
    },
    {
      "date": "2025-09-05",
      "count": "2577"
    },
    {
      "date": "2025-09-06",
      "count": "2581"
    },
    {
      "date": "2025-09-07",
      "count": "2581"
    },
    {
      "date": "2025-09-08",
      "count": "2585"
    },
    {
      "date": "2025-09-09",
      "count": "2587"
    },
    {
      "date": "2025-09-10",
      "count": "2591"
    },
    {
      "date": "2025-09-11",
      "count": "2591"
    },
    {
      "date": "2025-09-12",
      "count": "2593"
    },
    {
      "date": "2025-09-13",
      "count": "2594"
    },
    {
      "date": "2025-09-14",
      "count": "2594"
    },
    {
      "date": "2025-09-15",
      "count": "2594"
    },
    {
      "date": "2025-09-16",
      "count": "2597"
    },
    {
      "date": "2025-09-17",
      "count": "2598"
    },
    {
      "date": "2025-09-18",
      "count": "2602"
    },
    {
      "date": "2025-09-19",
      "count": "2604"
    },
    {
      "date": "2025-09-20",
      "count": "2605"
    },
    {
      "date": "2025-09-21",
      "count": "2605"
    },
    {
      "date": "2025-09-22",
      "count": "2604"
    },
    {
      "date": "2025-09-23",
      "count": "2604"
    },
    {
      "date": "2025-09-24",
      "count": "2605"
    },
    {
      "date": "2025-09-25",
      "count": "2607"
    },
    {
      "date": "2025-09-26",
      "count": "2609"
    },
    {
      "date": "2025-09-27",
      "count": "2609"
    },
    {
      "date": "2025-09-28",
      "count": "2608"
    },
    {
      "date": "2025-09-29",
      "count": "2608"
    },
    {
      "date": "2025-09-30",
      "count": "2609"
    },
    {
      "date": "2025-10-01",
      "count": "2612"
    },
    {
      "date": "2025-10-02",
      "count": "2613"
    },
    {
      "date": "2025-10-03",
      "count": "2617"
    },
    {
      "date": "2025-10-04",
      "count": "2618"
    },
    {
      "date": "2025-10-05",
      "count": "2620"
    },
    {
      "date": "2025-10-06",
      "count": "2621"
    },
    {
      "date": "2025-10-07",
      "count": "2623"
    },
    {
      "date": "2025-10-08",
      "count": "2624"
    },
    {
      "date": "2025-10-09",
      "count": "2628"
    },
    {
      "date": "2025-10-10",
      "count": "2631"
    },
    {
      "date": "2025-10-11",
      "count": "2629"
    },
    {
      "date": "2025-10-12",
      "count": "2630"
    },
    {
      "date": "2025-10-13",
      "count": "2631"
    },
    {
      "date": "2025-10-14",
      "count": "2632"
    },
    {
      "date": "2025-10-15",
      "count": "2633"
    },
    {
      "date": "2025-10-16",
      "count": "2635"
    },
    {
      "date": "2025-10-17",
      "count": "2637"
    },
    {
      "date": "2025-10-18",
      "count": "2639"
    },
    {
      "date": "2025-10-19",
      "count": "2639"
    },
    {
      "date": "2025-10-20",
      "count": "2639"
    },
    {
      "date": "2025-10-21",
      "count": "2639"
    },
    {
      "date": "2025-10-22",
      "count": "2641"
    },
    {
      "date": "2025-10-23",
      "count": "2641"
    },
    {
      "date": "2025-10-24",
      "count": "2640"
    },
    {
      "date": "2025-10-25",
      "count": "2641"
    },
    {
      "date": "2025-10-26",
      "count": "2641"
    },
    {
      "date": "2025-10-27",
      "count": "2641"
    },
    {
      "date": "2025-10-28",
      "count": "2641"
    },
    {
      "date": "2025-10-29",
      "count": "2643"
    },
    {
      "date": "2025-10-30",
      "count": "2642"
    },
    {
      "date": "2025-10-31",
      "count": "2645"
    },
    {
      "date": "2025-11-01",
      "count": "2645"
    },
    {
      "date": "2025-11-02",
      "count": "2644"
    },
    {
      "date": "2025-11-03",
      "count": "2645"
    },
    {
      "date": "2025-11-04",
      "count": "2647"
    },
    {
      "date": "2025-11-05",
      "count": "2651"
    },
    {
      "date": "2025-11-06",
      "count": "2654"
    },
    {
      "date": "2025-11-07",
      "count": "2654"
    },
    {
      "date": "2025-11-08",
      "count": "2655"
    },
    {
      "date": "2025-11-09",
      "count": "2655"
    },
    {
      "date": "2025-11-10",
      "count": "2655"
    },
    {
      "date": "2025-11-11",
      "count": "2655"
    },
    {
      "date": "2025-11-12",
      "count": "2656"
    },
    {
      "date": "2025-11-13",
      "count": "2657"
    }
  ]
}
